freertos_gdb/__init__.py
freertos_gdb/common.py
freertos_gdb/heap.py
freertos_gdb/queue.py
freertos_gdb/task.py
freertos_gdb/timer.py
wqtool_gdb-1.0.0.dist-info/LICENSE
wqtool_gdb-1.0.0.dist-info/METADATA
wqtool_gdb-1.0.0.dist-info/WHEEL
wqtool_gdb-1.0.0.dist-info/top_level.txt
wqtool_gdb-1.0.0.dist-info/RECORD
